notalib/__init__.py
notalib/array.py
notalib/array_test.py
notalib/combinator.py
notalib/combinator_test.py
notalib/date.py
notalib/date_test.py
notalib/deprecated.py
notalib/deprecated_test.py
notalib/dict.py
notalib/dict_test.py
notalib/django/__init__.py
notalib/django/auth.py
notalib/django/auth_test.py
notalib/django/bytes_stream.py
notalib/django/bytes_stream_test.py
notalib/django/clickhouse/__init__.py
notalib/django/clickhouse/base.py
notalib/django/clickhouse/base_test.py
notalib/django/clickhouse/mutations.py
notalib/django/clickhouse/mutations_test.py
notalib/django/clickhouse/profiler.py
notalib/django/clickhouse/profiler_test.py
notalib/django/clickhouse/wait.py
notalib/django/clickhouse/wait_test.py
notalib/django/colorlog.py
notalib/django/colorlog_test.py
notalib/django/filterset.py
notalib/django/filterset_test.py
notalib/django/formplus.py
notalib/django/formplus_test.py
notalib/django/http.py
notalib/django/http_test.py
notalib/django/request_time_middleware.py
notalib/django/request_time_middleware_test.py
notalib/django/stream.py
notalib/django/stream_test.py
notalib/django_xauth/__init__.py
notalib/django_xauth/apps.py
notalib/django_xauth/migrations/0001_initial.py
notalib/django_xauth/migrations/__init__.py
notalib/django_xauth/models.py
notalib/django_xauth/serializers.py
notalib/django_xauth/urls.py
notalib/django_xauth/views.py
notalib/django_xauth/views_test.py
notalib/file_iterator.py
notalib/file_iterator_test.py
notalib/filterset.py
notalib/filterset_test.py
notalib/format.py
notalib/format_test.py
notalib/git.py
notalib/git_test.py
notalib/hypertext.py
notalib/hypertext_test.py
notalib/pandas/__init__.py
notalib/pandas/pandasplus.py
notalib/pandas/pandasplus_test.py
notalib/polosa.py
notalib/polosa_test.py
notalib/range.py
notalib/range_test.py
notalib/tablib/__init__.py
notalib/tablib/dataset.py
notalib/tablib/dataset_test.py
notalib/tablib/shortcuts.py
notalib/tablib/shortcuts_test.py
notalib/test_fakes.py
notalib/time.py
notalib-2.6.0.dist-info/LICENSE
notalib-2.6.0.dist-info/METADATA
notalib-2.6.0.dist-info/WHEEL
notalib-2.6.0.dist-info/RECORD
