Metadata-Version: 2.1
Name: notalib
Version: 2.6.0
Summary: A collection of utility functions & classes
Home-page: https://github.com/m1kc/notalib
License: MIT
Keywords: utility,django,pandas
Author: m1kc (Max Musatov)
Author-email: m1kc@yandex.ru
Requires-Python: >=3.7.3,<4.0.0
Classifier: License :: OSI Approved :: MIT License
Classifier: Operating System :: OS Independent
Classifier: Programming Language :: Python :: 3
Classifier: Programming Language :: Python :: 3.8
Classifier: Programming Language :: Python :: 3.9
Classifier: Programming Language :: Python :: 3.10
Classifier: Programming Language :: Python :: 3.11
Classifier: Programming Language :: Python :: 3.12
Requires-Dist: arrow (>=0.14.0,<2.0.0)
Project-URL: Documentation, https://github.com/m1kc/notalib
Project-URL: Repository, https://github.com/m1kc/notalib.git
